oaemlib/__init__.py
oaemlib/edge.py
oaemlib/filepicker.py
oaemlib/gml.py
oaemlib/gml_provider.py
oaemlib/oaem.py
oaemlib/suntrack.py
oaemlib/wfs.py
oaemlib-0.2.0.dist-info/LICENSE
oaemlib-0.2.0.dist-info/METADATA
oaemlib-0.2.0.dist-info/WHEEL
oaemlib-0.2.0.dist-info/RECORD
